MANIFEST.in
README.rst
pyproject.toml
setup.cfg
setup.py
ai/__init__.py
ai/h2o/__init__.py
ai/h2o/sparkling/BackingJar.py
ai/h2o/sparkling/ExternalBackendConf.py
ai/h2o/sparkling/H2OConf.py
ai/h2o/sparkling/H2OContext.py
ai/h2o/sparkling/H2ODataFrameConverters.py
ai/h2o/sparkling/Initializer.py
ai/h2o/sparkling/InternalBackendConf.py
ai/h2o/sparkling/SharedBackendConf.py
ai/h2o/sparkling/SharedBackendConfUtils.py
ai/h2o/sparkling/VersionComponents.py
ai/h2o/sparkling/__init__.py
ai/h2o/sparkling/version.txt
ai/h2o/sparkling/ml/H2OStageBase.py
ai/h2o/sparkling/ml/Utils.py
ai/h2o/sparkling/ml/__init__.py
ai/h2o/sparkling/ml/algos/DistributionBasedH2OTrainFramePreparation.py
ai/h2o/sparkling/ml/algos/FamilyBasedH2OTrainFramePreparation.py
ai/h2o/sparkling/ml/algos/H2OAlgorithm.py
ai/h2o/sparkling/ml/algos/H2OAutoML.py
ai/h2o/sparkling/ml/algos/H2OAutoMLExtras.py
ai/h2o/sparkling/ml/algos/H2OCoxPH.py
ai/h2o/sparkling/ml/algos/H2ODRF.py
ai/h2o/sparkling/ml/algos/H2ODeepLearning.py
ai/h2o/sparkling/ml/algos/H2OEstimator.py
ai/h2o/sparkling/ml/algos/H2OExtendedIsolationForest.py
ai/h2o/sparkling/ml/algos/H2OGAM.py
ai/h2o/sparkling/ml/algos/H2OGBM.py
ai/h2o/sparkling/ml/algos/H2OGLM.py
ai/h2o/sparkling/ml/algos/H2OGridSearch.py
ai/h2o/sparkling/ml/algos/H2OGridSearchExtras.py
ai/h2o/sparkling/ml/algos/H2OIsolationForest.py
ai/h2o/sparkling/ml/algos/H2OKMeans.py
ai/h2o/sparkling/ml/algos/H2OKMeansExtras.py
ai/h2o/sparkling/ml/algos/H2ORuleFit.py
ai/h2o/sparkling/ml/algos/H2OStackedEnsemble.py
ai/h2o/sparkling/ml/algos/H2OStackedEnsembleExtras.py
ai/h2o/sparkling/ml/algos/H2OSupervisedAlgorithm.py
ai/h2o/sparkling/ml/algos/H2OSupervisedAlgorithmWithFoldColumn.py
ai/h2o/sparkling/ml/algos/H2OTreeBasedSupervisedAlgorithm.py
ai/h2o/sparkling/ml/algos/H2OTreeBasedUnsupervisedAlgorithm.py
ai/h2o/sparkling/ml/algos/H2OUnsupervisedAlgorithm.py
ai/h2o/sparkling/ml/algos/H2OXGBoost.py
ai/h2o/sparkling/ml/algos/__init__.py
h2o_pysparkling_3.0.egg-info/PKG-INFO
h2o_pysparkling_3.0.egg-info/SOURCES.txt
h2o_pysparkling_3.0.egg-info/dependency_links.txt
h2o_pysparkling_3.0.egg-info/requires.txt
h2o_pysparkling_3.0.egg-info/top_level.txt
